{
          "TYPE": "Sniper Rifle",
          "WEAPON": "Bite of the Fox",
          "ELEMENT": "Kinetic",
          "SLOT": "Kinetic",
          "AMMO": "Special",
          "ARCHETYPE": "Aggressive",
          "OBTAINED": "Iron Banner",
          "ROF/DRAW/CHARGE": "72",
          "IMPACT/BLAST": "90",
          "RANGE/ACCURACY/VELOCITY": "73",
          "STABILITY/EFFICIENCY": "28",
          "HANDLING": "32",
          "RELOAD/DEFENSE": "32",
          "AIM ASSIST": "41",
          "MAG": "3",
          "RECOIL DIRECTION": "68",
          "DPS MOST BOSSES": "13522",
          "TOTAL DAMAGE BOSSES": "191556",
          "DPS 2X BOSSES": "27043",
          "TOTAL DAMAGE 2X BOSSES": "383112",
          "PVP OPTIMAL TTK": "0.83",
          "PVP BODY TTK": "0.83"
}
